thomas/client/__build__
thomas/client/__init__.py
thomas/client/_version.py
thomas_client-0.1.0a19.dist-info/METADATA
thomas_client-0.1.0a19.dist-info/WHEEL
thomas_client-0.1.0a19.dist-info/top_level.txt
thomas_client-0.1.0a19.dist-info/RECORD
