Metadata-Version: 2.1
Name: thomas-client
Version: 0.1.0a19
Summary: Client for Thomas' RESTful API and webinterface
Home-page: https://github.com/mellesies/thomas-client
Author: Melle Sieswerda
Author-email: m.sieswerda@iknl.nl
License: UNKNOWN
Platform: UNKNOWN
Requires-Python: >= 3.6
Requires-Dist: requests
